{
  "__version": "0.5.1",
  "results": {
    "http://mdn-bcd-collector.appspot.com/tests/api/AudioContext/AudioContext": [
      {
        "info": {
          "code": "bcd.testConstructor(\"AudioContext\");",
          "exposure": "Window"
        },
        "message": "threw ReferenceError: Can't find variable: AudioContext",
        "name": "api.AudioContext.AudioContext",
        "result": null
      }
    ]
  },
  "userAgent": "Mozilla/5.0 (iPhone; CPU iPhone OS 13_2 like Mac OS X) AppleWebKit/605.1.15 (KHTML, like Gecko) GSA/111.0.314264656 Mobile/15E148 Safari/604.1"
}
